remote_rf/__init__.py
remote_rf/api_tokens.py
remote_rf/client.py
remote_rf/grpc_server.proto
remote_rf/grpc_server_pb2.py
remote_rf/grpc_server_pb2_grpc.py
remote_rf/serializer.py
remote_rf/server.py
remote_rf-0.0.2.dist-info/METADATA
remote_rf-0.0.2.dist-info/WHEEL
remote_rf-0.0.2.dist-info/licenses/LICENSE
remote_rf-0.0.2.dist-info/RECORD
