Metadata-Version: 2.3
Name: remote_rf
Version: 0.0.2
Summary: A python API to remotely access signal centric hardware.
Project-URL: Homepage, https://github.com/pypa/sampleproject
Project-URL: Issues, https://github.com/pypa/sampleproject/issues
Author-email: Ethan Ge <ethoGalaxy@gmail.com>
License-File: LICENSE
Classifier: License :: OSI Approved :: MIT License
Classifier: Operating System :: OS Independent
Classifier: Programming Language :: Python :: 3
Requires-Python: >=3.8
